{
  "nodeModelList": [
    {
      "title": "xxx",
      "index": "第四百二十条",
      "content": "xx"
    },
    {
      "title": "xxx",
      "index": "第四百二十一条",
      "content": "xx"
    },
    {
      "title": "xxx",
      "index": "第四百二十二条",
      "content": "xx"
    },
    {
      "title": "xxx",
      "index": "第四百二十三条",
      "content": "xx"
    },
    {
      "title": "xxx",
      "index": "第四百二十四条",
      "content": "xx"
    },
    {
      "title": "xxx",
      "index": "第四百二十五条",
      "content": "xx"
    },
    {
      "title": "xxx",
      "index": "第四百二十六条",
      "content": "xx"
    },
    {
      "title": "xxx",
      "index": "第四百二十七条",
      "content": "xx"
    },
    {
      "title": "xxx",
      "index": "第四百二十八条",
      "content": "xx"
    },
    {
      "title": "xxx",
      "index": "第四百二十九条",
      "content": "xx"
    },
    {
      "title": "xxx",
      "index": "第四百三十条",
      "content": "xx"
    },
    {
      "title": "xxx",
      "index": "第四百三十一条",
      "content": "xx"
    },
    {
      "title": "xxx",
      "index": "第四百三十二条",
      "content": "xx"
    },
    {
      "title": "xxx",
      "index": "第四百三十三条",
      "content": "xx"
    },
    {
      "title": "xxx",
      "index": "第四百三十四条",
      "content": "xx"
    },
    {
      "title": "xxx",
      "index": "第四百三十五条",
      "content": "xx"
    },
    {
      "title": "xxx",
      "index": "第四百三十六条",
      "content": "xx"
    },
    {
      "title": "xxx",
      "index": "第四百三十七条",
      "content": "xx"
    },
    {
      "title": "xxx",
      "index": "第四百三十八条",
      "content": "xx"
    },
    {
      "title": "xxx",
      "index": "第四百三十九条",
      "content": "xx"
    },
    {
      "title": "xxx",
      "index": "第四百四十条",
      "content": "xx"
    },
    {
      "title": "xxx",
      "index": "第四百四十一条",
      "content": "xx"
    },
    {
      "title": "xxx",
      "index": "第四百四十二条",
      "content": "xx"
    },
    {
      "title": "xxx",
      "index": "第四百四十三条",
      "content": "xx"
    },
    {
      "title": "xxx",
      "index": "第四百四十四条",
      "content": "xx"
    },
    {
      "title": "xxx",
      "index": "第四百四十五条",
      "content": "xx"
    },
    {
      "title": "xxx",
      "index": "第四百四十六条",
      "content": "xx"
    },
    {
      "title": "xxx",
      "index": "第四百四十七条",
      "content": "xx"
    },
    {
      "title": "xxx",
      "index": "第四百四十八条",
      "content": "xx"
    },
    {
      "title": "xxx",
      "index": "第四百四十九条",
      "content": "xx"
    },
    {
      "title": "xxx",
      "index": "第四百五十条",
      "content": "xx"
    },
    {
      "title": "xxx",
      "index": "第四百五十一条",
      "content": "xx"
    }
  ],
  "title": "第十章 军人违反职责罪"
}
